wwpdb/__init__.py
wwpdb/utils/__init__.py
wwpdb/utils/nmr/AlignUtil.py
wwpdb/utils/nmr/BMRBChemShiftStat.py
wwpdb/utils/nmr/BMRBCsStatUpdater.py
wwpdb/utils/nmr/ChemCompUpdater.py
wwpdb/utils/nmr/ChemCompUtil.py
wwpdb/utils/nmr/CifToNmrStar.py
wwpdb/utils/nmr/NmrDpConstant.py
wwpdb/utils/nmr/NmrDpFirstAid.py
wwpdb/utils/nmr/NmrDpMrSplitter.py
wwpdb/utils/nmr/NmrDpRegistry.py
wwpdb/utils/nmr/NmrDpRemediation.py
wwpdb/utils/nmr/NmrDpReport.py
wwpdb/utils/nmr/NmrDpUtility.py
wwpdb/utils/nmr/NmrDpValidation.py
wwpdb/utils/nmr/NmrVrptUtility.py
wwpdb/utils/nmr/README.md
wwpdb/utils/nmr/__init__.py
wwpdb/utils/nmr/ann/BMRBAnnTasks.py
wwpdb/utils/nmr/ann/OneDepAnnTasks.py
wwpdb/utils/nmr/ann/__init__.py
wwpdb/utils/nmr/ann/lib/adit_item_tbl_o.csv
wwpdb/utils/nmr/ann/lib/tagmap.csv
wwpdb/utils/nmr/bmrb_cs_stat/aa_filt.csv
wwpdb/utils/nmr/bmrb_cs_stat/aa_filt.pkl
wwpdb/utils/nmr/bmrb_cs_stat/aa_full.csv
wwpdb/utils/nmr/bmrb_cs_stat/aa_full.pkl
wwpdb/utils/nmr/bmrb_cs_stat/dna_filt.csv
wwpdb/utils/nmr/bmrb_cs_stat/dna_filt.pkl
wwpdb/utils/nmr/bmrb_cs_stat/dna_full.csv
wwpdb/utils/nmr/bmrb_cs_stat/dna_full.pkl
wwpdb/utils/nmr/bmrb_cs_stat/others.csv
wwpdb/utils/nmr/bmrb_cs_stat/others.pkl
wwpdb/utils/nmr/bmrb_cs_stat/rna_filt.csv
wwpdb/utils/nmr/bmrb_cs_stat/rna_filt.pkl
wwpdb/utils/nmr/bmrb_cs_stat/rna_full.csv
wwpdb/utils/nmr/bmrb_cs_stat/rna_full.pkl
wwpdb/utils/nmr/cs/AriaCSParserListener.py
wwpdb/utils/nmr/cs/AriaCSReader.py
wwpdb/utils/nmr/cs/BareCSLexer.py
wwpdb/utils/nmr/cs/BareCSParser.py
wwpdb/utils/nmr/cs/BareCSParserListener.py
wwpdb/utils/nmr/cs/BareCSReader.py
wwpdb/utils/nmr/cs/BaseCSParserListener.py
wwpdb/utils/nmr/cs/GarretCSLexer.py
wwpdb/utils/nmr/cs/GarretCSParser.py
wwpdb/utils/nmr/cs/GarretCSParserListener.py
wwpdb/utils/nmr/cs/GarretCSReader.py
wwpdb/utils/nmr/cs/NmrPipeCSLexer.py
wwpdb/utils/nmr/cs/NmrPipeCSParser.py
wwpdb/utils/nmr/cs/NmrPipeCSParserListener.py
wwpdb/utils/nmr/cs/NmrPipeCSReader.py
wwpdb/utils/nmr/cs/NmrStar2CSLexer.py
wwpdb_utils_nmr-0.49.2.dist-info/licenses/LICENSE
wwpdb_utils_nmr-0.49.2.dist-info/METADATA
wwpdb_utils_nmr-0.49.2.dist-info/WHEEL
wwpdb_utils_nmr-0.49.2.dist-info/top_level.txt
wwpdb_utils_nmr-0.49.2.dist-info/RECORD
