Metadata-Version: 2.4
Name: wwpdb.utils.nmr
Version: 0.49.2
Summary: wwPDB NMR utilities
Home-page: https://github.com/wwpdb/py-wwpdb_utils_nmr
Author: Ezra Peisach
Author-email: ezra.peisach@rcsb.org
License: Apache 2.0
Classifier: Development Status :: 3 - Alpha
Classifier: Intended Audience :: Developers
Classifier: Natural Language :: English
Classifier: License :: OSI Approved :: Apache Software License
Classifier: Programming Language :: Python
Classifier: Programming Language :: Python :: 3
Classifier: Programming Language :: Python :: 3.6
Classifier: Programming Language :: Python :: 3.7
Requires-Python: >=3.7
License-File: LICENSE
Requires-Dist: wwpdb.utils.config~=0.34
Requires-Dist: wwpdb.utils.align
Requires-Dist: pynmrstar>=3.2; python_version >= "3"
Requires-Dist: munkres; python_version >= "3"
Requires-Dist: mmcif
Requires-Dist: numpy
Requires-Dist: scikit-learn
Requires-Dist: rmsd
Requires-Dist: packaging
Requires-Dist: chardet
Requires-Dist: antlr4-python3-runtime~=4.13.0; python_version >= "3"
Requires-Dist: striprtf
Requires-Dist: datetime
Requires-Dist: dataclasses; python_version == "3.6"
Provides-Extra: dev
Requires-Dist: check-manifest; extra == "dev"
Provides-Extra: test
Requires-Dist: coverage; extra == "test"
Dynamic: author
Dynamic: author-email
Dynamic: classifier
Dynamic: description
Dynamic: home-page
Dynamic: license
Dynamic: license-file
Dynamic: provides-extra
Dynamic: requires-dist
Dynamic: requires-python
Dynamic: summary
